customs_tax/__init__.py
customs_tax/container_security_fee/__init__.py
customs_tax/container_security_fee/csf.py
customs_tax/landed_cost/__init__.py
customs_tax/landed_cost/components_of_lc/__init__.py
customs_tax/landed_cost/components_of_lc/arrastre_charge/__init__.py
customs_tax/landed_cost/components_of_lc/arrastre_charge/outports/__init__.py
customs_tax/landed_cost/components_of_lc/arrastre_charge/outports/ac_outports.py
customs_tax/landed_cost/components_of_lc/arrastre_charge/pom_micp/__init__.py
customs_tax/landed_cost/components_of_lc/arrastre_charge/pom_micp/containerized_dangerous_cargo/__init__.py
customs_tax/landed_cost/components_of_lc/arrastre_charge/pom_micp/containerized_dangerous_cargo/containerized_dangerous_cargo.py
customs_tax/landed_cost/components_of_lc/arrastre_charge/pom_micp/fcl/__init__.py
customs_tax/landed_cost/components_of_lc/arrastre_charge/pom_micp/fcl/full_containerized_cargo.py
customs_tax/landed_cost/components_of_lc/arrastre_charge/pom_micp/lcl/__init__.py
customs_tax/landed_cost/components_of_lc/arrastre_charge/pom_micp/lcl/bulk_break_bulk_cargo.py
customs_tax/landed_cost/components_of_lc/bank_charge/__init__.py
customs_tax/landed_cost/components_of_lc/bank_charge/bc.py
customs_tax/landed_cost/components_of_lc/brokerage_fee/__init__.py
customs_tax/landed_cost/components_of_lc/brokerage_fee/bf_formal_entry.py
customs_tax/landed_cost/components_of_lc/customs_documentary_stamp/__init__.py
customs_tax/landed_cost/components_of_lc/customs_documentary_stamp/cds.py
customs_tax/landed_cost/components_of_lc/customs_duty/__init__.py
customs_tax/landed_cost/components_of_lc/customs_duty/cud.py
customs_tax/landed_cost/components_of_lc/dutiable_value/__init__.py
customs_tax/landed_cost/components_of_lc/dutiable_value/dv.py
customs_tax/landed_cost/components_of_lc/import_processing_fee/__init__.py
customs_tax/landed_cost/components_of_lc/import_processing_fee/ipf.py
customs_tax/landed_cost/components_of_lc/wharfage_due/__init__.py
customs_tax-0.0.3.dist-info/LICENSE
customs_tax-0.0.3.dist-info/METADATA
customs_tax-0.0.3.dist-info/WHEEL
customs_tax-0.0.3.dist-info/top_level.txt
customs_tax-0.0.3.dist-info/RECORD
