Metadata-Version: 2.1
Name: customs_tax
Version: 0.0.3
Summary: A package for calculating customs taxes, duties, and other charges.
Home-page: https://github.com/iaaan05/python-customs-tax-package
Author: Iaaan05
Author-email: iaaan100500@gmail.com
Classifier: Intended Audience :: Developers
Classifier: License :: OSI Approved :: MIT License
Classifier: Programming Language :: Python :: 3.11
Requires-Python: >=3.11
License-File: LICENSE
